vilha/__init__.py
vilha/client.py
vilha/connection.py
vilha/datastructures.py
vilha/di/__init__.py
vilha/di/container.py
vilha/di/datastructures.py
vilha/di/utils.py
vilha/main.py
vilha/protocol.py
vilha/server.py
vilha/starlette/__init__.py
vilha/starlette/applications.py
vilha/transport/__init__.py
vilha/transport/aiormq.py
vilha/types.py
vilha-0.0.2.dist-info/METADATA
vilha-0.0.2.dist-info/WHEEL
vilha-0.0.2.dist-info/RECORD
