Metadata-Version: 2.1
Name: vilha
Version: 0.0.2
Summary: ASGI server for amqp rpc protocol
Author: Your Name
Author-email: you@example.com
Requires-Python: >=3.10,<4.0
Classifier: Programming Language :: Python :: 3
Classifier: Programming Language :: Python :: 3.10
Classifier: Programming Language :: Python :: 3.11
Classifier: Programming Language :: Python :: 3.12
Requires-Dist: aiormq (>=6.8.0,<7.0.0)
Requires-Dist: starlette (>=0.37.2,<0.38.0)
Requires-Dist: typing-extensions (>=4.10.0,<5.0.0)
